cli/__init__.py
cli/_version_.py
cli/dictionary.py
cli/folder.py
cli/ok.py
cli/plugins.py
cli/toollist.py
cli/utils.py
cli/plugins/cal.py
cli/plugins/cc.py
cli/plugins/git.py
mymodule/__init__.py
mymodule/align.py
mymodule/mypath.py
mymodule/rotate_logger.py
mymodule/seq.py
mymodule/tool.py
mymodule/NUPACK/_NUPACK.py
mymodule/NUPACK/__init__.py
mymodule/NUPACK/nupack3.0.6/bin/.exist
mymodule/NUPACK/nupack3.0.6/bin/complexes
mymodule/NUPACK/nupack3.0.6/bin/concentrations
mymodule/NUPACK/nupack3.0.6/bin/count
mymodule/NUPACK/nupack3.0.6/bin/defect
mymodule/NUPACK/nupack3.0.6/bin/design
mymodule/NUPACK/nupack3.0.6/bin/distributions
mymodule/NUPACK/nupack3.0.6/bin/energy
mymodule/NUPACK/nupack3.0.6/bin/mfe
mymodule/NUPACK/nupack3.0.6/bin/pairs
mymodule/NUPACK/nupack3.0.6/bin/pfunc
mymodule/NUPACK/nupack3.0.6/bin/prob
mymodule/NUPACK/nupack3.0.6/bin/sample
mymodule/NUPACK/nupack3.0.6/bin/subopt
mymodule/NUPACK/nupack3.0.6/lib/.exist
mymodule/NUPACK/nupack3.0.6/lib/Makefile
mymodule/NUPACK/nupack3.0.6/lib/libdesign_pfunc_utils.a
mymodule/NUPACK/nupack3.0.6/lib/libmt19937.a
mymodule/NUPACK/nupack3.0.6/lib/libpfunc.a
mymodule/NUPACK/nupack3.0.6/lib/libutils.a
mymodule/NUPACK/nupack3.0.6/parameters/dna1998.dG
mymodule/NUPACK/nupack3.0.6/parameters/dna1998.dH
mymodule/NUPACK/nupack3.0.6/parameters/rna1995.dG
mymodule/NUPACK/nupack3.0.6/parameters/rna1995.dH
mymodule/NUPACK/nupack3.0.6/parameters/rna1999.dG
mymodule/RNAstructure/Error_handling.py
mymodule/RNAstructure/RNAstructure_wrap.py
mymodule/RNAstructure/_RNAstructure.py
mymodule/RNAstructure/_RNAstructure_wrap.so
mymodule/RNAstructure/__init__.py
mymodule/RNAstructure/readme.txt
mymodule/RNAstructure/data_tables/autodetect.txt
mymodule/RNAstructure/data_tables/average_ensemble_defect.model
mymodule/RNAstructure/data_tables/b-test.coaxial.dg
mymodule/RNAstructure/data_tables/b-test.coaxial.dh
mymodule/RNAstructure/data_tables/b-test.coaxstack.dg
mymodule/RNAstructure/data_tables/b-test.coaxstack.dh
huik_module-0.1.22.dist-info/LICENSE
huik_module-0.1.22.dist-info/METADATA
huik_module-0.1.22.dist-info/WHEEL
huik_module-0.1.22.dist-info/entry_points.txt
huik_module-0.1.22.dist-info/top_level.txt
huik_module-0.1.22.dist-info/RECORD
