Metadata-Version: 2.1
Name: huik-module
Version: 0.1.22
Summary: Modules for my scripts.
Home-page: https://github.com/rocksnow1942/mymodule
Author: Hui Kang
Author-email: rocksnow1942@gmail.com
License: UNKNOWN
Platform: UNKNOWN
Classifier: Programming Language :: Python :: 3
Classifier: License :: OSI Approved :: MIT License
Classifier: Operating System :: OS Independent
Requires-Python: >=3.6
Requires-Dist: psutil
Requires-Dist: click
Requires-Dist: colorama
Requires-Dist: terminaltables
